icinga/__init__.py
icinga/listener.py
robotframework_listener_icinga-1.0.4.dist-info/licenses/AUTHORS.rst
robotframework_listener_icinga-1.0.4.dist-info/licenses/LICENSE
robotframework_listener_icinga-1.0.4.dist-info/METADATA
robotframework_listener_icinga-1.0.4.dist-info/WHEEL
robotframework_listener_icinga-1.0.4.dist-info/top_level.txt
robotframework_listener_icinga-1.0.4.dist-info/RECORD
