Metadata-Version: 2.4
Name: robotframework-listener-icinga
Version: 1.0.4
Summary: A Robot Framework listener for reporting via Icinga2 API.
Home-page: https://gitlab.com/uhbs/robotframework-listener-icinga
Author: Dominik Riva
Author-email: dominik.riva@usb.ch
License: Apache-2.0
Project-URL: Changelog, https://gitlab.com/dominik.riva/robotframework-listener-icinga/blob/master/CHANGELOG.rst
Project-URL: Issue Tracker, https://gitlab.com/dominik.riva/robotframework-listener-icinga/issues
Classifier: Development Status :: 2 - Pre-Alpha
Classifier: Intended Audience :: Developers
Classifier: License :: OSI Approved :: Apache Software License
Classifier: Operating System :: Unix
Classifier: Operating System :: POSIX
Classifier: Operating System :: Microsoft :: Windows
Classifier: Programming Language :: Python
Classifier: Programming Language :: Python :: 3
Classifier: Programming Language :: Python :: 3 :: Only
Classifier: Programming Language :: Python :: 3.8
Classifier: Programming Language :: Python :: 3.9
Classifier: Programming Language :: Python :: 3.10
Classifier: Programming Language :: Python :: 3.11
Classifier: Programming Language :: Python :: Implementation :: CPython
Classifier: Programming Language :: Python :: Implementation :: PyPy
Classifier: Topic :: Utilities
Requires-Python: >=3.8
License-File: LICENSE
License-File: AUTHORS.rst
Requires-Dist: linuxfabrik-lib<1000,>=2.0.0.0
Requires-Dist: rpaframework>=27.5.2
Dynamic: author
Dynamic: author-email
Dynamic: classifier
Dynamic: description
Dynamic: home-page
Dynamic: license
Dynamic: license-file
Dynamic: project-url
Dynamic: requires-dist
Dynamic: requires-python
Dynamic: summary
